{
  "type": "武器",
  "title": "法器",
  "name": "翡玉法球",
  "introduce": "由璃月北郊绝云间出产的硬玉雕琢而成的法器。小巧轻盈，经久耐用，江湖人称「翡玉丸」。",
  "access": "祈愿",
  "rarity": 3,
  "mainStat": "元素精通",
  "mainValue": "94",
  "baseATK": 448,
  "ascensionMaterials": [
    ["孤云寒林的光砂", "孤云寒林的辉岩", "孤云寒林的圣骸", "孤云寒林的神体"],
    ["猎兵祭刀", "特工祭刀", "督察长祭刀", "寻宝鸦印", "藏银鸦印", "攫金鸦印"]
  ],
  "time": "【周一/四/日】",
  "skillName": "激流",
  "skillContent": "触发蒸发、感电、冰冻或水元素扩散反应后的<span class=\"desc-number\">12</span>秒内，攻击力提高<span class=\"desc-number recolor\">20%/25%/30%/35%/40%</span>。"
}
